[
  {
    "idCategory":"120",
    "idStore":"12020",
    "id":"120-20-1001",
    "idProduct":"120201001",
    "name":"guarana",
    "unit":"1",
    "extent":"L",
    "brand":"backus",
    "price":"",
    "newPrice":"3.50",
    "store":"bebidas",
    "tags":["gaseosas"],
    "categories":["soda"],
    "stock":true,
    "styleTag":{
      "name":"guarana original",
      "color_back_top":"#de6a2f",
      "color_back_bottom":"#de6a2f",
      "color_text":"#fafcfc"
    },
    "description":"",
    "image":{
      "url_01":"https://raw.githubusercontent.com/Riszart/backend_3dgina/main/img_products/backus/gaseosas/120201001-guarana.webp",
      "url_02":"",
      "url_03":""
      }
  },
  {
    "idCategory":"120",
    "idStore":"12020",
    "id":"120-20-1002",
    "idProduct":"120201002",
    "name":"guarana",
    "unit":"3",
    "extent":"L",
    "brand":"backus",
    "price":"",
    "newPrice":"8.50",
    "store":"bebidas",
    "tags":["gaseosas"],
    "categories":["soda"],
    "stock":true,
    "styleTag":{
      "name":"guarana original",
      "color_back_top":"#de6a2f",
      "color_back_bottom":"#de6a2f",
      "color_text":"#fafcfc"
    },
    "description":" guarana original de 3010 ml",
    "image":{
      "url_01":"https://raw.githubusercontent.com/Riszart/backend_3dgina/main/img_products/backus/gaseosas/120201002-guarana.webp",
      "url_02":"",
      "url_03":""
      }
  },
  {
    "idCategory":"120",
    "idStore":"12020",
    "id":"120-20-1003",
    "idProduct":"120201003",
    "name":"coca cola",
    "unit":"600",
    "extent":"ml",
    "brand":"linley",
    "price":"",
    "newPrice":"3.20",
    "store":"bebidas",
    "tags":["gaseosas"],
    "categories":["soda"],
    "stock":true,
    "styleTag":{
      "name":"coca cola original",
      "color_back_top":"#fe0a1a",
      "color_back_bottom":"#fe0a1a",
      "color_text":"#fafcfc"
    },
    "description":"",
    "image":{
      "url_01":"https://raw.githubusercontent.com/Riszart/backend_3dgina/main/img_products/lindley/gaseosas/120201003-coca_cola.webp",
      "url_02":"",
      "url_03":""
      }
  },
  {
    "idCategory":"120",
    "idStore":"12020",
    "id":"120-20-1004",
    "idProduct":"120201004",
    "name":"coca cola - retornable",
    "unit":"1",
    "extent":"L",
    "brand":"linley",
    "price":"",
    "newPrice":"4.00",
    "store":"bebidas",
    "tags":["gaseosas", "retornable"],
    "categories":["soda"],
    "stock":true,
    "styleTag":{
      "name":"coca cola original",
      "color_back_top":"#fe0a1a",
      "color_back_bottom":"#fe0a1a",
      "color_text":"#fafcfc"
    },
    "description":"",
    "image":{
      "url_01":"https://raw.githubusercontent.com/Riszart/backend_3dgina/main/img_products/lindley/gaseosas/120201004-coca_cola.webp",
      "url_02":"",
      "url_03":""
      }
  },
  {
    "idCategory":"120",
    "idStore":"12020",
    "id":"120-20-1005",
    "idProduct":"120201005",
    "name":"coca cola - retornable",
    "unit":"1,5",
    "extent":"L",
    "brand":"linley",
    "price":"",
    "newPrice":"5.50",
    "store":"bebidas",
    "tags":["gaseosas", "retornable"],
    "categories":["soda"],
    "stock":true,
    "styleTag":{
      "name":"coca cola original",
      "color_back_top":"#fe0a1a",
      "color_back_bottom":"#fe0a1a",
      "color_text":"#fafcfc"
    },
    "description":"",
    "image":{
      "url_01":"https://raw.githubusercontent.com/Riszart/backend_3dgina/main/img_products/lindley/gaseosas/120201005-coca_cola.webp",
      "url_02":"",
      "url_03":""
      }
  },
  {
    "idCategory":"120",
    "idStore":"12020",
    "id":"120-20-1006",
    "idProduct":"120201006",
    "name":"coca cola - retornable",
    "unit":"2,5",
    "extent":"L",
    "brand":"linley",
    "price":"",
    "newPrice":"7.00",
    "store":"bebidas",
    "tags":["gaseosas", "retornable"],
    "categories":["soda"],
    "stock":true,
    "styleTag":{
      "name":"coca cola original",
      "color_back_top":"#fe0a1a",
      "color_back_bottom":"#fe0a1a",
      "color_text":"#fafcfc"
    },
    "description":"",
    "image":{
      "url_01":"https://raw.githubusercontent.com/Riszart/backend_3dgina/main/img_products/lindley/gaseosas/120201006-coca_cola.webp",
      "url_02":"",
      "url_03":""
      }
  },
  {
    "idCategory":"120",
    "idStore":"12020",
    "id":"120-20-1007",
    "idProduct":"120201007",
    "name":"coca cola",
    "unit":"3",
    "extent":"L",
    "brand":"linley",
    "price":"",
    "newPrice":"12.00",
    "store":"bebidas",
    "tags":["gaseosas", "no retornable"],
    "categories":["soda"],
    "stock":true,
    "styleTag":{
      "name":"coca cola original",
      "color_back_top":"#fe0a1a",
      "color_back_bottom":"#fe0a1a",
      "color_text":"#fafcfc"
    },
    "description":"",
    "image":{
      "url_01":"https://raw.githubusercontent.com/Riszart/backend_3dgina/main/img_products/lindley/gaseosas/120201007-coca_cola.webp",
      "url_02":"",
      "url_03":""
      }
  },
  {
    "idCategory":"120",
    "idStore":"12020",
    "id":"120-20-1008",
    "idProduct":"120201008",
    "name":"inca kola",
    "unit":"600",
    "extent":"ml",
    "brand":"linley",
    "price":"",
    "newPrice":"3.20",
    "store":"bebidas",
    "tags":["gaseosas", "no retornable"],
    "categories":["soda"],
    "stock":true,
    "styleTag":{
      "name":"inca kola original",
      "color_back_top":"#ffdf1d",
      "color_back_bottom":"#ffdf1d",
      "color_text":"#030303"
    },
    "description":"",
    "image":{
      "url_01":"https://raw.githubusercontent.com/Riszart/backend_3dgina/main/img_products/lindley/gaseosas/120201008-inca_kola.webp",
      "url_02":"",
      "url_03":""
      }
  },
  {
    "idCategory":"120",
    "idStore":"12020",
    "id":"120-20-1009",
    "idProduct":"120201009",
    "name":"inca kola - retornable",
    "unit":"650",
    "extent":"ml",
    "brand":"linley",
    "price":"",
    "newPrice":"3.00",
    "store":"bebidas",
    "tags":["gaseosas", "retornable"],
    "categories":["soda"],
    "stock":true,
    "styleTag":{
      "name":"inca kola original",
      "color_back_top":"#ffdf1d",
      "color_back_bottom":"#ffdf1d",
      "color_text":"#030303"
    },
    "description":"",
    "image":{
      "url_01":"https://raw.githubusercontent.com/Riszart/backend_3dgina/main/img_products/lindley/gaseosas/120201009-inca_kola.webp",
      "url_02":"",
      "url_03":""
      }
  },
  {
    "idCategory":"120",
    "idStore":"12020",
    "id":"120-20-1010",
    "idProduct":"120201010",
    "name":"inca kola - retornable",
    "unit":"1",
    "extent":"L",
    "brand":"linley",
    "price":"",
    "newPrice":"4.00",
    "store":"bebidas",
    "tags":["gaseosas","retornable"],
    "categories":["soda"],
    "stock":true,
    "styleTag":{
      "name":"inca kola original",
      "color_back_top":"#ffdf1d",
      "color_back_bottom":"#ffdf1d",
      "color_text":"#030303"
    },
    "description":"",
    "image":{
      "url_01":"https://raw.githubusercontent.com/Riszart/backend_3dgina/main/img_products/lindley/gaseosas/120201010-inca_kola.webp",
      "url_02":"",
      "url_03":""
      }
  },
  {
    "idCategory":"120",
    "idStore":"12020",
    "id":"120-20-1011",
    "idProduct":"120201011",
    "name":"inca kola - retornable",
    "unit":"1,5",
    "extent":"L",
    "brand":"linley",
    "price":"",
    "newPrice":"5.50",
    "store":"bebidas",
    "tags":["gaseosas","retornable"],
    "categories":["soda"],
    "stock":true,
    "styleTag":{
      "name":"inca kola original",
      "color_back_top":"#ffdf1d",
      "color_back_bottom":"#ffdf1d",
      "color_text":"#030303"
    },
    "description":"",
    "image":{
      "url_01":"https://raw.githubusercontent.com/Riszart/backend_3dgina/main/img_products/lindley/gaseosas/120201011-inca_kola.webp",
      "url_02":"",
      "url_03":""
      }
  },
  {
    "idCategory":"120",
    "idStore":"12020",
    "id":"120-20-1012",
    "idProduct":"120201012",
    "name":"inca kola - retornable",
    "unit":"2,5",
    "extent":"L",
    "brand":"linley",
    "price":"",
    "newPrice":"7.00",
    "store":"bebidas",
    "tags":["gaseosas","retornable"],
    "categories":["soda"],
    "stock":true,
    "styleTag":{
      "name":"inca kola original",
      "color_back_top":"#ffdf1d",
      "color_back_bottom":"#ffdf1d",
      "color_text":"#030303"
    },
    "description":"",
    "image":{
      "url_01":"https://raw.githubusercontent.com/Riszart/backend_3dgina/main/img_products/lindley/gaseosas/120201012-inca_kola.webp",
      "url_02":"",
      "url_03":""
      }
  },
  {
    "idCategory":"120",
    "idStore":"12020",
    "id":"120-20-1013",
    "idProduct":"120201013",
    "name":"inca kola",
    "unit":"3",
    "extent":"L",
    "brand":"linley",
    "price":"13.00",
    "newPrice":"12.00",
    "store":"bebidas",
    "tags":["gaseosas","no retornable"],
    "categories":["soda"],
    "styleTag":{
      "name":"inca kola original",
      "color_back_top":"#ffdf1d",
      "color_back_bottom":"#ffdf1d",
      "color_text":"#030303"
    },
    "stock":true,
    "description":"",
    "image":{
      "url_01":"https://raw.githubusercontent.com/Riszart/backend_3dgina/main/img_products/lindley/gaseosas/120201013-inka_kola.webp",
      "url_02":"",
      "url_03":""
      }
  },
  {
    "idCategory":"120",
    "idStore":"12020",
    "id":"120-20-1014",
    "idProduct":"120201014",
    "name":"fanta - kola inglesa",
    "unit":"500",
    "extent":"ml",
    "brand":"linley",
    "price":"",
    "newPrice":"2.50",
    "store":"bebidas",
    "tags":["gaseosas","no retornable"],
    "categories":["soda"],
    "stock":true,
    "styleTag":{
      "name":"kola inglesa",
      "color_back_top":"#fe1d22",
      "color_back_bottom":"#fe1d22",
      "color_text":"#fafcfc"
    },
    "description":"",
    "image":{
      "url_01":"https://raw.githubusercontent.com/Riszart/backend_3dgina/main/img_products/lindley/gaseosas/120201014-fanta_cola_inglesa.webp",
      "url_02":"",
      "url_03":""
      }
  },
  {
    "idCategory":"120",
    "idStore":"12020",
    "id":"120-20-1015",
    "idProduct":"120201015",
    "name":"fanta - naranja",
    "unit":"3",
    "extent":"L",
    "brand":"linley",
    "price":"",
    "newPrice":"8.50",
    "store":"bebidas",
    "tags":["gaseosas","no retornable"],
    "categories":["soda"],
    "stock":true,
    "styleTag":{
      "name":"naranja",
      "color_back_top":"#fc8704",
      "color_back_bottom":"#fc8704",
      "color_text":"#fafcfc"
    },
    "description":"",
    "image":{
      "url_01":"https://raw.githubusercontent.com/Riszart/backend_3dgina/main/img_products/lindley/gaseosas/120201015-fanta_naranja.webp",
      "url_02":"",
      "url_03":""
      }
  },
  {
    "idCategory":"120",
    "idStore":"12020",
    "id":"120-20-1016",
    "idProduct":"120201016",
    "name":"sprite",
    "unit":"3",
    "extent":"L",
    "brand":"linley",
    "price":"",
    "newPrice":"8.50",
    "store":"bebidas",
    "tags":["gaseosas","no retornable"],
    "categories":["soda"],
    "stock":true,
    "styleTag":{
      "name":"lima - limon",
      "color_back_top":"#02ae4b",
      "color_back_bottom":"#02ae4b",
      "color_text":"#fafcfc"
    },
    "description":"",
    "image":{
      "url_01":"https://raw.githubusercontent.com/Riszart/backend_3dgina/main/img_products/lindley/gaseosas/120201016-sprite.webp",
      "url_02":"",
      "url_03":""
      }
  },
  {
    "idCategory":"120",
    "idStore":"12020",
    "id":"120-20-1017",
    "idProduct":"120201017",
    "name":"cool",
    "unit":"350",
    "extent":"ml",
    "brand":"ism",
    "price":"",
    "newPrice":"1.00",
    "store":"bebidas",
    "tags":["gaseosas","no retornable"],
    "categories":["soda"],
    "stock":true,
    "styleTag":{
      "name":"cool",
      "color_back_top":"#fe6716",
      "color_back_bottom":"#f78c0c",
      "color_text":"#fff"
    },
    "description":"",
    "more":[
      {
        "id":"120-20-1017-1",
        "idProduct":"1202010171",
        "name":"cool cola negra",
        "image":"https://raw.githubusercontent.com/Riszart/backend_3dgina/main/img_products/aje/ism/1202010171-cool.webp",
        "stock":true
      },
      {
        "id":"120-20-1017-2",
        "idProduct":"1202010172",
        "name":"cool piña",
        "image":"https://raw.githubusercontent.com/Riszart/backend_3dgina/main/img_products/aje/ism/1202010172-cool.webp",
        "stock":true
      },
      {
        "id":"120-20-1017-3",
        "idProduct":"1202010173",
        "name":"cool amarilla",
        "image":"https://raw.githubusercontent.com/Riszart/backend_3dgina/main/img_products/aje/ism/1202010173-cool.webp",
        "stock":false
      }
    ],
    "image":{
      "url_01":"https://raw.githubusercontent.com/Riszart/backend_3dgina/main/img_products/aje/ism/1202010171-cool.webp",
      "url_02":"",
      "url_03":""
      }
  },
  {
    "idCategory":"120",
    "idStore":"12020",
    "id":"120-20-1018",
    "idProduct":"120201018",
    "name":"",
    "unit":"350",
    "extent":"ml",
    "brand":"ism",
    "price":"",
    "newPrice":"1.00",
    "store":"bebidas",
    "tags":["gaseosas","no retornable"],
    "categories":["soda"],
    "stock":false,
    "styleTag":{
      "name":"cool piña",
      "color_back_top":"#fe6716",
      "color_back_bottom":"#f78c0c",
      "color_text":"#fff"
    },
    "description":"",
    "image":{
      "url_01":"https://raw.githubusercontent.com/Riszart/backend_3dgina/main/img_products/aje/ism/120201018-cool.webp",
      "url_02":"",
      "url_03":""
      }
  },
  {
    "idCategory":"120",
    "idStore":"12020",
    "id":"120-20-1019",
    "idProduct":"120201019",
    "name":"",
    "unit":"350",
    "extent":"ml",
    "brand":"ism",
    "price":"",
    "newPrice":"1.00",
    "store":"bebidas",
    "tags":["gaseosas","no retornable"],
    "categories":["soda"],
    "stock":false,
    "styleTag":{
      "name":"cool amarilla",
      "color_back_top":"#fe6716",
      "color_back_bottom":"#f78c0c",
      "color_text":"#fff"
    },
    "description":"",
    "image":{
      "url_01":"https://raw.githubusercontent.com/Riszart/backend_3dgina/main/img_products/aje/ism/120201019-cool.webp",
      "url_02":"",
      "url_03":""
      }
  },
  {
    "idCategory":"120",
    "idStore":"12020",
    "id":"120-20-1020",
    "idProduct":"120201020",
    "name":"kr ",
    "unit":"350",
    "extent":"ml",
    "brand":"ism",
    "price":"",
    "newPrice":"1.00",
    "store":"bebidas",
    "tags":["gaseosas","no retornable"],
    "categories":["soda"],
    "stock":true,
    "styleTag":{
      "name":"kr",
      "color_back_top":"#fe6716",
      "color_back_bottom":"#f78c0c",
      "color_text":"#fff"
    },
    "description":"",
    "more":[
        {
          "id":"120-20-1020-1",
          "idProduct":"1202010201",
          "name":"kr negra",
          "image":"https://raw.githubusercontent.com/Riszart/backend_3dgina/main/img_products/aje/ism/1202010201-kr.webp",
          "stock":true
        },
        {
          "id":"120-20-1020-2",
          "idProduct":"1202010202",
          "name":"kr roja",
          "image":"https://raw.githubusercontent.com/Riszart/backend_3dgina/main/img_products/aje/ism/1202010202-kr.webp",
          "stock":true
        },
        {
          "id":"120-20-1020-3",
          "idProduct":"1202010203",
          "name":"kr naranja",
          "image":"https://raw.githubusercontent.com/Riszart/backend_3dgina/main/img_products/aje/ism/1202010203-kr.webp",
          "stock":true
        },
        {
          "id":"120-20-1020-4",
          "idProduct":"1202010204",
          "name":"kr limon",
          "image":"https://raw.githubusercontent.com/Riszart/backend_3dgina/main/img_products/aje/ism/1202010204-kr.webp",
          "stock":true
        },
        {
          "id":"120-20-1020-5",
          "idProduct":"1202010205",
          "name":"kr amarilla",
          "image":"https://raw.githubusercontent.com/Riszart/backend_3dgina/main/img_products/aje/ism/1202010205-kr.webp",
          "stock":true
        }
      ],
    "image":{
      "url_01":"https://raw.githubusercontent.com/Riszart/backend_3dgina/main/img_products/aje/ism/1202010201-kr.webp"
      }
  },
  {
    "idCategory":"120",
    "idStore":"12020",
    "id":"120-20-1021",
    "idProduct":"120201021",
    "name":"",
    "unit":"350",
    "extent":"ml",
    "brand":"ism",
    "price":"",
    "newPrice":"1.00",
    "store":"bebidas",
    "tags":["gaseosas","no retornable"],
    "categories":["soda"],
    "stock":false,
    "styleTag":{
      "name":"kr roja",
      "color_back_top":"#fe6716",
      "color_back_bottom":"#f78c0c",
      "color_text":"#fff"
    },
    "description":"",
    "image":{
      "url_01":"https://raw.githubusercontent.com/Riszart/backend_3dgina/main/img_products",
      "url_02":"",
      "url_03":""
      }
  },
  {
    "idCategory":"120",
    "idStore":"12020",
    "id":"120-20-1022",
    "idProduct":"120201022",
    "name":"",
    "unit":"350",
    "extent":"ml",
    "brand":"ism",
    "price":"",
    "newPrice":"1.00",
    "store":"bebidas",
    "tags":["gaseosas","no retornable"],
    "categories":["soda"],
    "stock":false,
    "styleTag":{
      "name":"kr naranja",
      "color_back_top":"#fe6716",
      "color_back_bottom":"#f78c0c",
      "color_text":"#fff"
    },
    "description":"",
    "image":{
      "url_01":"https://raw.githubusercontent.com/Riszart/backend_3dgina/main/img_products",
      "url_02":"",
      "url_03":""
      }
  },
  {
    "idCategory":"120",
    "idStore":"12020",
    "id":"120-20-1023",
    "idProduct":"120201023",
    "name":"",
    "unit":"350",
    "extent":"ml",
    "brand":"ism",
    "price":"",
    "newPrice":"1.00",
    "store":"bebidas",
    "tags":["gaseosas","no retornable"],
    "categories":["soda"],
    "stock":false,
    "styleTag":{
      "name":"kr limon",
      "color_back_top":"#fe6716",
      "color_back_bottom":"#f78c0c",
      "color_text":"#fff"
    },
    "description":"",
    "image":{
      "url_01":"https://raw.githubusercontent.com/Riszart/backend_3dgina/main/img_products",
      "url_02":"",
      "url_03":""
      }
  },
  {
    "idCategory":"120",
    "idStore":"12020",
    "id":"120-20-1024",
    "idProduct":"120201024",
    "name":"kr - negra",
    "unit":"3",
    "extent":"L",
    "brand":"ism",
    "price":"",
    "newPrice":"6.50",
    "store":"bebidas",
    "tags":["gaseosas","no retornable"],
    "categories":["soda"],
    "stock":true,
    "styleTag":{
      "name":"kr negra",
      "color_back_top":"#fe6716",
      "color_back_bottom":"#f78c0c",
      "color_text":"#fff"
    },
    "description":"",
    "image":{
      "url_01":"https://raw.githubusercontent.com/Riszart/backend_3dgina/main/img_products/aje/ism/120201024-kr.webp",
      "url_02":"",
      "url_03":""
      }
  },
  {
    "idCategory":"120",
    "idStore":"12020",
    "id":"120-20-1025",
    "idProduct":"120201025",
    "name":"big cola",
    "unit":"350",
    "extent":"ml",
    "brand":"aje",
    "price":"",
    "newPrice":"1.00",
    "store":"bebidas",
    "tags":["gaseosas","no retornable"],
    "categories":["soda"],
    "stock":true,
    "styleTag":{
      "name":"big cola",
      "color_back_top":"#df0a1e",
      "color_back_bottom":"#df0a1e",
      "color_text":"#fbfdfd"
    },
    "description":"",
    "image":{
      "url_01":"https://raw.githubusercontent.com/Riszart/backend_3dgina/main/img_products/aje/bebidas/120201025-big_cola.webp",
      "url_02":"",
      "url_03":""
      }
  },
  {
    "idCategory":"120",
    "idStore":"12020",
    "id":"120-20-1026",
    "idProduct":"120201026",
    "name":"big cola",
    "unit":"1,7",
    "extent":"L",
    "brand":"aje",
    "price":"",
    "newPrice":"4.00",
    "store":"bebidas",
    "tags":["gaseosas","no retornable"],
    "categories":["soda"],
    "stock":true,
    "styleTag":{
      "name":"big cola",
      "color_back_top":"#df0a1e",
      "color_back_bottom":"#df0a1e",
      "color_text":"#fbfdfd"
    },
    "description":"",
    "image":{
      "url_01":"https://raw.githubusercontent.com/Riszart/backend_3dgina/main/img_products/aje/bebidas/120201026-big_cola.webp",
      "url_02":"",
      "url_03":""
      }
  },
  {
    "idCategory":"120",
    "idStore":"12020",
    "id":"120-20-1027",
    "idProduct":"120201027",
    "name":"big cola",
    "unit":"3",
    "extent":"L",
    "brand":"aje",
    "price":"",
    "newPrice":"7.00",
    "store":"bebidas",
    "tags":["gaseosas","no retornable"],
    "categories":["soda"],
    "stock":true,
    "styleTag":{
      "name":"big cola",
      "color_back_top":"#df0a1e",
      "color_back_bottom":"#df0a1e",
      "color_text":"#fbfdfd"
    },
    "description":"",
    "image":{
      "url_01":"https://raw.githubusercontent.com/Riszart/backend_3dgina/main/img_products/aje/bebidas/120201027-big_cola.webp",
      "url_02":"",
      "url_03":""
      }
  },
  {
    "idCategory":"120",
    "idStore":"12020",
    "id":"120-20-1028",
    "idProduct":"120201028",
    "name":"oro",
    "unit":"350",
    "extent":"ml",
    "brand":"aje",
    "price":"",
    "newPrice":"1.00",
    "store":"bebidas",
    "tags":["gaseosas","no retornable"],
    "categories":["soda"],
    "stock":true,
    "styleTag":{
      "name":"sabor de oro",
      "color_back_top":"#faea00",
      "color_back_bottom":"#faea00",
      "color_text":"#fbfdfd"
    },
    "description":"",
    "image":{
      "url_01":"https://raw.githubusercontent.com/Riszart/backend_3dgina/main/img_products/aje/bebidas/120201028-oro.webp",
      "url_02":"",
      "url_03":""
      }
  },
  {
    "idCategory":"120",
    "idStore":"12020",
    "id":"120-20-1029",
    "idProduct":"120201029",
    "name":"oro",
    "unit":"1,7",
    "extent":"L",
    "brand":"aje",
    "price":"",
    "newPrice":"4.00",
    "store":"bebidas",
    "tags":["gaseosas","no retornable"],
    "categories":["soda"],
    "stock":true,
    "styleTag":{
      "name":"sabor de oro",
      "color_back_top":"#faea00",
      "color_back_bottom":"#faea00",
      "color_text":"#fbfdfd"
    },
    "description":"",
    "image":{
      "url_01":"https://raw.githubusercontent.com/Riszart/backend_3dgina/main/img_products/aje/bebidas/120201029-oro.webp",
      "url_02":"",
      "url_03":""
      }
  },
  {
    "idCategory":"120",
    "idStore":"12020",
    "id":"120-20-1030",
    "idProduct":"120201030",
    "name":"pepsi",
    "unit":"3",
    "extent":"L",
    "brand":"pepsico",
    "price":"",
    "newPrice":"8.00",
    "store":"bebidas",
    "tags":["gaseosas","no retornable"],
    "categories":["soda"],
    "stock":true,
    "styleTag":{
      "name":"pepsi",
      "color_back_top":"#0252a4",
      "color_back_bottom":"#0252a4",
      "color_text":"#fbfdfd"
    },
    "description":"",
    "image":{
      "url_01":"https://raw.githubusercontent.com/Riszart/backend_3dgina/main/img_products/pepsico/120201030-pepsi.webp",
      "url_02":"",
      "url_03":""
      }
  },
  {
    "idCategory":"120",
    "idStore":"12020",
    "id":"120-20-1031",
    "idProduct":"120201031",
    "name":"pepsi",
    "unit":"1,5",
    "extent":"L",
    "brand":"pepsico",
    "price":"",
    "newPrice":"4.00",
    "store":"bebidas",
    "tags":["gaseosas","no retornable"],
    "categories":["soda"],
    "stock":true,
    "styleTag":{
      "name":"pepsi",
      "color_back_top":"#0252a4",
      "color_back_bottom":"#0252a4",
      "color_text":"#fbfdfd"
    },
    "description":"",
    "image":{
      "url_01":"https://raw.githubusercontent.com/Riszart/backend_3dgina/main/img_products/pepsico/120201031-pepsi.webp",
      "url_02":"",
      "url_03":""
      }
  },
  {
    "idCategory":"120",
    "idStore":"12020",
    "id":"120-20-1032",
    "idProduct":"120201032",
    "name":"pepsi",
    "unit":"2",
    "extent":"L",
    "brand":"pepsico",
    "price":"",
    "newPrice":"5.00",
    "store":"bebidas",
    "tags":["gaseosas","no retornable"],
    "categories":["soda"],
    "stock":true,
    "styleTag":{
      "name":"pepsi",
      "color_back_top":"#0252a4",
      "color_back_bottom":"#0252a4",
      "color_text":"#fbfdfd"
    },
    "description":"",
    "image":{
      "url_01":"https://raw.githubusercontent.com/Riszart/backend_3dgina/main/img_products/pepsico/120201032-pepsi.webp",
      "url_02":"",
      "url_03":""
      }
  }
]